setup.py
gush/__init__.py
gush/gush.py
gush.egg-info/PKG-INFO
gush.egg-info/SOURCES.txt
gush.egg-info/dependency_links.txt
gush.egg-info/entry_points.txt
gush.egg-info/top_level.txt