Metadata-Version: 1.1
Name: gush
Version: 1.0.0
Summary: Shorten urls with Google URL shortening service
Home-page: https://github.com/durden/gush
Author: Luke Lee
Author-email: durdenmisc@gmail.com
License: MIT
Platform: any
Classifier: Development Status :: 4 - Beta
Classifier: Environment :: Console
Classifier: Intended Audience :: Developers
Classifier: Intended Audience :: End Users/Desktop
Classifier: Natural Language :: English
Classifier: Operating System :: OS Independent
Classifier: Topic :: System :: Archiving
